[
    [
        {
            "tagName": "সুরা সমূহ",
            "dataType": "surah"
        },
        {
            "tagName": "নামাজ",
            "dataType": "namaz"
        },
        {
            "tagName": "মাসনুন দু'আ",
            "dataType": "dowa"
        }
    ],
    [
        {
            "id": 1,
            "title": "নামাজের ফরজ ১৩টি",
            "tags": "fajr",
            "blogImg": "./assets/images/blog/blog.webp",
            "publishedDate": "৬ নভেম্বর ২০২৪",
            "readTime": "10 min read",
            "subtitle": "নামাজে শুরু করার আগে এবং নামাজের ভিতরে কিছু গুরুত্বপূর্ণ কাজ রয়েছে, যেগুলো অবশ্যই পালন করতে হয়। এই কাজগুলোর যে কোনো একটি বাদ পড়লে নামাজ শুদ্ধ হয় না। এই অপরিহার্য কাজগুলোকে নামাজের ফরজ বলা হয়। নামাজের ফরজ মোট ১৩টি, যা দুটি ভাগে বিভক্ত: ১. আহকাম  ২. আরকান।",
            "content": [
                "<p>নামাজে শুরু করার আগে এবং নামাজের ভিতরে কিছু গুরুত্বপূর্ণ কাজ রয়েছে, যেগুলো অবশ্যই পালন করতে হয়। এই কাজগুলোর যে কোনো একটি বাদ পড়লে নামাজ শুদ্ধ হয় না। এই অপরিহার্য কাজগুলোকে নামাজের ফরজ বলা হয়। নামাজের ফরজ মোট ১৩টি, যা দুটি ভাগে বিভক্ত: ১. আহকাম  ২. আরকান</p>",
                "<h2>নামাজের আহকাম</h2>",
                "<ul><li>নামাজের বাহিরে যে ফরজ কাজগুলো রয়েছে, সেগুলোকে নামাজের আহকাম বলে। আহকাম ৭টি:</li><li><strong>১. শরীর পাক</strong> : প্রয়োজনমতো ওজু, গোসল বা তায়াম্মুমের মাধ্যমে শারীরিক পবিত্রতা অর্জন করা।</li><li><strong>২. কাপড় পাক</strong> : নামাজর সময় পরিধানের যা-ই থাকবে তা পবিত্র হওয়া আবশ্যক।</li><li><strong>৩. নামাজের জায়গা পাক</strong> : নামাজের আদায়ের স্থান পাক হওয়া।</li><li><strong>৪. সতর ঢাকা</strong> : পুরুষের নাভি থেকে হাঁটু পর্যন্ত এবং নারীর সমস্ত শরীর (মুখমণ্ডল, হাতের কব্জি এবং পায়ের পাতা ছাড়া) ঢেকে রাখা।</li><li><strong>৫. কিবলামুখী হওয়া</strong> : কাবার দিকে মুখ করে সালাত আদায় করা।</li><li><strong>৬. ওয়াক্তমত নামাজ পড়া</strong> : নির্ধারিত সময়ের মধ্যে নামায আদায় করা।</li> <li><strong>৭.নামাজের নিয়ত করা</strong> : যে নামাজ আদায় করা হয়, তার জন্য মনে মনে নিয়্যত করা</li></ul>",
                "<h2>নামাজের আরকান</h2>",
                "<ul><li>নামাজের ভিতরে যে ফরজ কাজগুলো রয়েছে, সেগুলোকে নামাজের আরকান বলে। আরকান ৬টি</li><li><strong>১. তাকবীরে তাহরীমা বলা</strong> : আল্লাহু আকবার বলে নামাজ শুরু করা।</li><li><strong>২. কেয়াম করা</strong> : কোন অসুবিধা না থাকলে সোজা হয়ে দাঁড়িয়ে নামাজ পড়া। তবে দাঁড়াতে অক্ষম হলে বসে বা শুয়ে যে কোনো অবস্থায় সালাত আদায় করতে হবে।</li><li><strong>৩. কিরাত পড়া</strong> : কুরআন মজিদের কিছু অংশ পাঠ করা। আল্লাহ তায়ালা বলেন তোমরা কুরআন থেকে যতটুকু সহজ হয়, ততটুকু পড়।</li><li><strong>৪. রুকু করা</strong> : প্রত্যেক রাকাতে একবার রুকু করা ফরজ।</li><li><strong>৫. সিজদাহ করা</strong> : প্রতি রাকাতে দুটি সিজদাহ করা ফরজ।</li><li><strong>৬. শেষ বৈঠকে বসা</strong> : যে বৈঠকে তাশাহুদ, দরুদ, ও দোয়া মাসুরা পড়ে সালাতের শেষ করা হয়।</li></ul>",
                "<h2>নামাযের ফরয পালন না করলে</h2>",
                "<p>নামাযের যে কোনো ফরয ইচ্ছাকৃতভাবে ছেড়ে দিলে বা ভুলে গেলে নামায বাতিল হয়ে যায়। সঠিকভাবে নামায আদায়ের জন্য প্রত্যেক মুসলিমের উচিত নামাযের ফরযগুলো সম্পর্কে সচেতন থাকা এবং তা যথাযথভাবে পালন করা।</p>"
            ]
        },
        {
            "id": 2,
            "title": "নামাজের ওয়াজিব ১৪টি",
            "tags": "fajr",
            "blogImg": "./assets/images/blog/blog.webp",
            "publishedDate": "৬ নভেম্বর ২০২৪",
            "readTime": "10 min read",
            "subtitle": "ওয়াজিব মানে অবশ্য পালনীয়। নামাজে কোন ওয়াজিব ছুটে গেলে সাহু সিজদা দিলে নামাজ আদায় হয়ে যায়। তবে ইচ্ছাকৃত কোন ওয়াজিব বাদ দিলে পুনরায় নামাজ আদায় করতে হয়। নামাজের ওয়াজিব বা আবশ্যক ১৪টি কাজ হলো:",
            "content": [
                "<p>ওয়াজিব মানে অবশ্য পালনীয়। নামাজে কোন ওয়াজিব ছুটে গেলে সাহু সিজদা দিলে নামাজ আদায় হয়ে যায়। তবে ইচ্ছাকৃতভাবে কোন ওয়াজিব বাদ দিলে নামায শুদ্ধ হবে না এবং পুনরায় নামাজ আদায় করতে হবে। নামাজের ওয়াজিব বা আবশ্যক ১৪টি কাজ হলো:</p>",
                "<ul><li>১. প্রত্যেক রাকাতে সূরা ফাতিহা পড়া।</li><li>২. সূরা ফাতিহার সাথে অন্য যেকোন সূরা মিলানো।</li><li>৩. রুকু, সেজদায় দেরী করা।</li><li>৪. রুকু হতে সোজা হয়ে দাঁড়িয়ে দেরী করা। (অর্থাৎ কমপক্ষে এক তাসবিহ পরিমাণ দেরি করা)।</li><li>৫. দুই সিজদার মাঝখানে সোজা হয়ে বসা।</li><li>৬. দরমিয়ানী বৈঠক (অর্থাৎ তিন অথবা চার রাকাতবিশিষ্ট নামাজে, প্রথম দুই রাকাআতের পর বসা)।</li><li>৭. উভয় বৈঠকে তাশাহহুদ পড়া। (অর্থাৎ তিন অথবা চার রাকাতবিশিষ্ট নামাজে উভয় বৈঠকে তাশাহহুদ পড়া)।</li><li>৮. ইমামের জন্য কেরাত আস্তে এবং জোরে পড়া।</li><li>৯. বিতর নামাজে দোয়া কুনুত পড়া।</li><li>১০. দুই ঈদের নামাজে অতিরিক্ত ছয় তাকবির বলা।</li><li>১১. প্রত্যেক ফরয নামাযের প্রথম দুই রাকাতকে কেরাতের জন্য নির্ধারিত করা।</li><li>১২. প্রত্যেক রাকাআতের ফরযগুলোর তারতীব(ধারাবাহিকতা) ঠিক রাখা।</li><li>১৩. প্রত্যেক রাকাতের ওয়াজিব গুলাের তারতীব(ধারাবাহিকতা) ঠিক রাখা।</li><li>১৪. আসসালামু আলাইকুম ওয়ারাহমাতুল্লাহ বলে সালাত শেষ করা।</li></ul>",
                "<h2>সাহু সিজদা (ভুলের সিজদা) আদার করার নিয়ম</h2>",
                "<p>নামাজের শেষ বৈঠকে তাশাহহুদ পড়ার পর ডান দিকে সালাম ফিরিয়ে দুটি সিজদাহ দিতে হবে। দুটি সিজদাহ দেওয়ার পর তাশাহহুদ, দরুদ শরীফ ও দোয়া মাসুরা পড়ে আসসালামু আলাইকুম ওয়া রাহমাতুল্লাহ বলে নামাজ শেষ করতে হয়।</p>"
            ]
        },
        {
            "id": 3,
            "title": "অজু ভঙ্গের কারণ সমূহ",
            "tags": "fajr",
            "blogImg": "./assets/images/blog/ablution.png",
            "publishedDate": "৬ নভেম্বর ২০২৪",
            "readTime": "10 min read",
            "subtitle": "ইসলামে নামাজ ও অন্যান্য ইবাদতের জন্য পবিত্র থাকা খুবই জরুরি। পবিত্রতা অর্জনের জন্য অজু আবশ্যক। বিভিন্ন কারণে অজু ভঙ্গ হয়ে গেলে, ইবাদতের জন্য নতুন করে অজু করা আবশ্যক।",
            "content": [
                "<p>ইসলামে নামাজ ও অন্যান্য ইবাদতের জন্য পবিত্র থাকা খুবই জরুরি। পবিত্রতা অর্জনের জন্য অজু আবশ্যক। বিভিন্ন কারণে অজু ভঙ্গ হয়ে গেলে, ইবাদতের জন্য নতুন করে অজু করা আবশ্যক। যেসব কারণে অজু নষ্ট হয়ে যায় তার বিস্তারিত বিবরণ নিচে দেওয়া হলো।</p>",
                "<h2>অজু ভঙ্গের কারণ সমূহ</h2>",
                "<ul><li>১. পায়খানা-প্রস্রাবের রাস্তা দিয়ে কোনো কিছু বাহির হওয়া।</li><li>২. মুখ ভরে বমি হওয়া।</li><li>৩. শরীরের কোনো জায়গা থেকে রক্ত, পুঁজ, পানি ইত্যাদি বের হয়ে গড়িয়ে পড়া।</li><li>৪. নামাজে উঁচস্বরে হাসিলে।</li><li>৫. চিত বা কাত হয়ে ঘুম যাওয়া।</li><li>৬. পাগল, মাতাল বা অচেতন হলে অজু ভঙ্গ হয়ে যাবে।</li><li>৭. থুথুর সঙ্গে রক্তের ভাগ সমান বা বেশী হওয়া।</li></ul>"
            ]
        },
        {
            "id": 4,
            "title": "গোসলের ফরজ কয়টি ও কী কী",
            "tags": "fajr",
            "blogImg": "./assets/images/blog/blog.webp",
            "publishedDate": "৬ নভেম্বর ২০২৪",
            "readTime": "10 min read",
            "subtitle": "গোসল শব্দের অর্থ ধৌত করা। শরিয়তের পরিভাষায়, পবিত্রতা অর্জনের উদ্দেশ্য পানি দ্বারা  সমস্ত শরীর ধৌত করাকে গোসল বলে।",
            "content": [
                "<p>গোসল শব্দের অর্থ ধৌত করা। শরিয়তের পরিভাষায়, পবিত্রতা অর্জনের উদ্দেশ্য পানি দ্বারা  সমস্ত শরীর ধৌত করাকে গোসল বলে।</p>",
                "<h2>গোসলের ফরজ তিনটি</h2>",
                "<ul><li>১. গড়গড়ার সাথে কুলি করা। তবে রোজাদার গড়গড়া করবে না।</li><li>২. নাকে পানি দেওয়া।</li><li>৩. সমস্ত শরীর ধৌত করা।</li></ul>",
                "<h2>গোসল ফরজ হওয়ার কারণ</h2>",
                "<ul><li>১. স্বপ্নদোষ হলে।</li><li>২. স্ত্রী সহবাস করলে।</li><li>৩. ঘুম অথবা জাগ্রত অবস্থায় শারীরিক উত্তেজনার সঙ্গে বীর্যপাত হলে।</li><li>৪. স্বামীর লিঙ্গের অগ্রভাগ স্ত্রীর গোপনাঙ্গে প্রবেশ করলে (বীর্যপাত ঘটুক বা না ঘটুক)।</li><li>৫. নারীদের হায়েজ বা নিফাস হলে।</li><li>৬. সমকাম কিংবা হস্ত মৈথুন করে বীর্যপাত ঘটালে।</li><li></ul>"
            ]
        },
        {
            "id": 5,
            "title": "গোসল করার সুন্নত পদ্ধতি",
            "tags": "fajr",
            "blogImg": "./assets/images/blog/blog.webp",
            "publishedDate": "৬ নভেম্বর ২০২৪",
            "readTime": "10 min read",
            "subtitle": "গোসল শব্দের অর্থ ধৌত করা। শরিয়তের পরিভাষায়, পবিত্রতা অর্জনের উদ্দেশ্য পানি দ্বারা  সমস্ত শরীর ধৌত করাকে গোসল বলে।",
            "content": [
                "<p>গোসল শব্দের অর্থ ধৌত করা। শরিয়তের পরিভাষায়, পবিত্রতা অর্জনের উদ্দেশ্য পানি দ্বারা  সমস্ত শরীর ধৌত করাকে গোসল বলে।</p>",
                "<h2>গোসলের সুন্নত সমূহ</h2>",
                "<ul><li>১. গোসল শুরু করার আগে বিসমিল্লাহ পড়া।</li><li>২. পবিত্রতা অর্জনের নিয়ত করা।</li><li>৩. উভয় হাতের কব্জি পর্যন্ত তিনবার ধৌত করা।</li><li>৪.  লজ্জাস্থান ভালো করে ধৌত করা।</li><li>৫. কাপড় বা শরীরে নাপাকি লেগে থাকলে তা ভালো করে ধৌত করা।</li><li>৬. গোসলের আগে অজু করা।</li><li>৭. সমস্ত শরীর তিনবার ধৌত করা।</li></ul>"
            ]
        },
        {
            "id": 6,
            "title": "গোসল কত প্রকার ও কী কী?",
            "tags": "fajr",
            "blogImg": "./assets/images/blog/blog.webp",
            "publishedDate": "৬ নভেম্বর ২০২৪",
            "readTime": "10 min read",
            "subtitle": "গোসল চার প্রকার: ১. ফরজ গোসল, ২. ওয়াজিব গোসল, ৩. সুন্নত গোসল, ৪. মুস্তাহাব গোসল। ফরজ গোসলঃ এমন কতগুলো কাজ আছে, যেগুলো করলে গোসল ছাড়া পবিত্রতা অর্জন করা যায় না। এরুপ গোসলকে ফরজ গোসল বলে। যথা-",
            "content": [
                "<ul><li><strong>ফরজ গোসলঃ </strong>এমন কতগুলো কাজ আছে, যেগুলো করলে গোসল ছাড়া পবিত্রতা অর্জন করা যায় না। এরুপ গোসলকে ফরজ গোসল বলে।</li><li>১. স্বপ্নদোষ হলে।</li><li>২. স্ত্রী সহবাস করলে।</li><li>৩. ঘুম অথবা জাগ্রত অবস্থায় শারীরিক উত্তেজনার সঙ্গে বীর্যপাত হলে।</li><li>৪. স্বামীর লিঙ্গের অগ্রভাগ স্ত্রীর গোপনাঙ্গে প্রবেশ করলে (বীর্যপাত ঘটুক বা না ঘটুক)।</li><li>৫. নারীদের হায়েজ বা নিফাস হলে।</li><li>৬. সমকাম কিংবা হস্ত মৈথুন করে বীর্যপাত ঘটালে।</li></ul>",
                "<ul><li><strong>ওয়াজিব গোসলঃ </strong>ওয়াজিব গোসলঃ হাদীসে যে গোসল করানোকে অত্যাবশ্যকীয় বলে নির্দেশ দেয়া হয়েছে, তাই ওয়াজিব গোসল। যেমনঃ</li><li>১. মৃত ব্যক্তিকে গোসল দেয়া।</li><li>২. স্বপ্নদোষ দ্বারা ছেলে বালেগ হলে।</li><li>৩. হায়েয বা স্বপ্নদোষ দ্বারা মেয়ে বালেগ হলে।</li></ul>",
                "<ul><li><strong>সুন্নত গোসলঃ </strong>রাসুল (সাঃ) বিশেষ বিশেষ কাজে যে গোসলের আদেশ দিয়েছেন, তাকে সুন্নত গোসল বলে। যেমনঃ</li><li>১. শুক্রবারে জুম'আর নামাজের জন্য গোসল করা।</li><li>২. দুই ঈদের নামাযের জন্য গোসল করা।</li><li>৩. আরাফাতের দিনে গোসল করা।</li><li>৪. ইহরামের জন্য গোসল করা।</li></ul>",
                "<ul><li><strong>মুস্তাহাব গোসলঃ </strong>কৃতজ্ঞতা পোষণ স্বরুপ বা ভাল কাজে হাত দেয়ার সময় যে গোসল করা হয়, তাকে মুস্তাহাব গোসল বলে। যেমনঃ</li><li>১. গুনাহ থেকে তাওবা করার জন্য।</li><li>২. মৃত ব্যক্তিকে গোসল দেওয়ার পর নিজে গোসল করা।</li></ul>"
            ]
        },
        {
            "id": 7,
            "title": "নামাজের সুন্নত সমূহ",
            "tags": "fajr",
            "blogImg": "./assets/images/blog/blog.webp",
            "publishedDate": "৬ নভেম্বর ২০২৪",
            "readTime": "10 min read",
            "subtitle": "১ 'আল্লাহু আকবার' বলার সময় পুরুষ কানের লতি পর্যন্ত এবং নারী কাঁধ পর্যন্ত দু’হাত উত্তোলন করা। ২ 'আল্লাহু আকবার' বলার সময় দুই হাতের আঙুলগুলো স্বাভাবিক অবস্থায় খোলা রাখা।",
            "content": [
                "<h2>নামাজের সুন্নত সমূহ</h2>",
                "<ul><li>১ 'আল্লাহু আকবার' বলার সময় পুরুষ কানের লতি পর্যন্ত এবং নারী কাঁধ পর্যন্ত দু’হাত উত্তোলন করা।</li><li>২ 'আল্লাহু আকবার' বলার সময় দুই হাতের আঙুলগুলো স্বাভাবিক অবস্থায় খোলা রাখা।</li><li>৩ 'আল্লাহু আকবার' বলে পুরুষের নাভী বরাবর এবং মহিলার বুকের উপর হাত বাধা।</li><li>৪ আউযুবিল্লাহ ও বিসমিল্লাহ পড়া।</li><li>৫ সানা পড়া।</li><li>৬ আলহামদুর পর আমীন বলা।</li><li>৭ রুকু এবং সিজদায় যাওয়ার সময় তাকবীর বলা।</li><li>৮ রুকুতে 'সুবহানা রাব্বিয়াল আযীম' তিনবার বলা।</li><li>৯ রুকু হতে সোজা হয়ে দাঁড়াবার সময় ইমাম 'সামি আল্লহু লিমান হামিদাহ' এবং মুক্তাদি 'রাব্বানা লাকাল হামদ' বলা। একাকী নামায পড়লে 'সামি আল্লহু লিমান হামিদাহ' এবং 'রাব্বানা লাকাল হামদ' উভয় বলতে হবে।</li><li>১০ সিজদায় যাওয়ার সময় প্রথমে হাঁটু, তারপর হাত, তারপর নাক এবং কপাল রাখা।</li><li>১১ তাশাহুদ পড়ার সময় আশহাদু আল লাইলাহা বলার সময় শাহাদাত আঙুলগুল দ্বারা ইশারা করা।</li><li>১২ শেষ বৈঠকে তাশাহুদ পড়ার পর দরুদ শরীফ ও দোয়ায়ে মাসূরা পড়া।</li><li>১৩ সিজদায় 'সুবহানা রাব্বিয়াল আলা' তিনবার বলা।</li><li>১৪ ফরজ নামাজের তৃতীয় ও চতুর্থ রাকাতে শুধুমাত্র সুরা ফাতিহা পড়া।</li><li>১৫ প্রথমে ডানে এবং পরে বামে সালাম ফিরিয়ে নামায শেষ করা।</li></ul>"
            ]
        }
    ]
]